ashford/__init__.py
ashford/base.py
ashford/core.py
ashford/foundry.py
ashford/registry.py
ashford/unified.py
ashford/validate.py
ashford-0.1.5.dist-info/LICENSE
ashford-0.1.5.dist-info/WHEEL
ashford-0.1.5.dist-info/METADATA
ashford-0.1.5.dist-info/RECORD
