Metadata-Version: 2.1
Name: ashford
Version: 0.1.5
Summary: factory, registration, and validation tools for python
Home-page: https://github.com/WithPrecedent/ashford
License: Apache-2.0
Author: corey rayburn yung
Author-email: coreyrayburnyung@gmail.com
Requires-Python: >=3.9,<4.0
Classifier: License :: OSI Approved :: Apache Software License
Classifier: Programming Language :: Python :: 3
Classifier: Programming Language :: Python :: 3.9
Classifier: Programming Language :: Python :: 3.10
Requires-Dist: camina (>=0.1.11,<0.2.0)
Requires-Dist: miller (>=0.1.6,<0.2.0)
Project-URL: Repository, https://github.com/WithPrecedent/ashford
